retrrry/__init__.py
retrrry-3.0.5.dist-info/LICENSE
retrrry-3.0.5.dist-info/WHEEL
retrrry-3.0.5.dist-info/METADATA
retrrry-3.0.5.dist-info/RECORD
