Metadata-Version: 2.1
Name: retrrry
Version: 3.0.5
Summary: Retry for Python3. No dependency.
Home-page: https://github.com/yaojiach/retrrry
License: Apache-2.0
Author: JC
Author-email: jc@jucyai.com
Requires-Python: >=3.6,<4.0
Classifier: License :: OSI Approved :: Apache Software License
Classifier: Programming Language :: Python :: 3
Classifier: Programming Language :: Python :: 3.10
Classifier: Programming Language :: Python :: 3.6
Classifier: Programming Language :: Python :: 3.7
Classifier: Programming Language :: Python :: 3.8
Classifier: Programming Language :: Python :: 3.9
Project-URL: Repository, https://github.com/yaojiach/retrrry
